PYRJrenderer/__init__.py
PYRJrenderer/custom_exception.py
PYRJrenderer/logger.py
PYRJrenderer/site.py
PYRJrenderer/youtube.py
PYRJrenderer-0.0.3.dist-info/LICENSE
PYRJrenderer-0.0.3.dist-info/METADATA
PYRJrenderer-0.0.3.dist-info/WHEEL
PYRJrenderer-0.0.3.dist-info/top_level.txt
PYRJrenderer-0.0.3.dist-info/RECORD
