Metadata-Version: 2.1
Name: PYRJrenderer
Version: 0.0.3
Summary: A Python package for rendering
Home-page: https://github.com/Rohii1515/PYRJrenderer
Author: Rohii1515
Author-email: rohidasjondhale1515@gmail.com
License: MIT
Project-URL: Bug Tracker, https://github.com/Rohii1515/PYRJrenderer/issues
Classifier: Programming Language :: Python :: 3.8
Classifier: Programming Language :: Python :: 3.9
Classifier: Programming Language :: Python :: 3.10
Classifier: Programming Language :: Python :: 3.11
Classifier: Operating System :: OS Independent
License-File: LICENSE
Requires-Dist: ensure
Requires-Dist: py-youtube
Provides-Extra: testing
Requires-Dist: pytest ; extra == 'testing'
Requires-Dist: mypy ; extra == 'testing'
Requires-Dist: flake8 ; extra == 'testing'
Requires-Dist: tox ; extra == 'testing'
Requires-Dist: black ; extra == 'testing'
